sangkuriang_ideal/__init__.py
sangkuriang_ideal/cli.py
sangkuriang_ideal/core/__init__.py
sangkuriang_ideal/core/initial_conditions.py
sangkuriang_ideal/core/solver.py
sangkuriang_ideal/io/__init__.py
sangkuriang_ideal/io/config_manager.py
sangkuriang_ideal/io/data_handler.py
sangkuriang_ideal/utils/__init__.py
sangkuriang_ideal/utils/logger.py
sangkuriang_ideal/utils/timer.py
sangkuriang_ideal/visualization/__init__.py
sangkuriang_ideal/visualization/animator.py
sangkuriang_ideal_solver-0.0.5.dist-info/LICENSE
sangkuriang_ideal_solver-0.0.5.dist-info/METADATA
sangkuriang_ideal_solver-0.0.5.dist-info/WHEEL
sangkuriang_ideal_solver-0.0.5.dist-info/entry_points.txt
sangkuriang_ideal_solver-0.0.5.dist-info/RECORD
